capital_finder/__init__.py
capital_finder/run.py
capital_finder/resources/capital.json
find_capital-1.0.0.data/data/capital_finder/resources/capital.json
find_capital-1.0.0.dist-info/METADATA
find_capital-1.0.0.dist-info/WHEEL
find_capital-1.0.0.dist-info/entry_points.txt
find_capital-1.0.0.dist-info/top_level.txt
find_capital-1.0.0.dist-info/RECORD
